weworkhelper/WeworkHelper.py
weworkhelper/__init__.py
weworkhelper-0.0.2.dist-info/METADATA
weworkhelper-0.0.2.dist-info/WHEEL
weworkhelper-0.0.2.dist-info/top_level.txt
weworkhelper-0.0.2.dist-info/RECORD
