Metadata-Version: 2.1
Name: weworkhelper
Version: 0.0.2
Summary: send messages through wework
Home-page: UNKNOWN
Author: skygongque
Author-email: 1243650225@qq.com
License: UNKNOWN
Platform: UNKNOWN
Classifier: License :: OSI Approved :: MIT License
Classifier: Programming Language :: Python :: 3
Classifier: Intended Audience :: Developers
Classifier: Operating System :: OS Independent
Requires-Dist: requests
